wxautox4/__init__.py
wxautox4/__main__.py
wxautox4/exceptions.py
wxautox4/languages.py
wxautox4/logger.py
wxautox4/msgs/__init__.py
wxautox4/msgs/base.cp311-win_amd64.pyd
wxautox4/msgs/base.pyi
wxautox4/msgs/friend.cp311-win_amd64.pyd
wxautox4/msgs/mattr.cp311-win_amd64.pyd
wxautox4/msgs/mattr.pyi
wxautox4/msgs/msg.cp311-win_amd64.pyd
wxautox4/msgs/mtype.cp311-win_amd64.pyd
wxautox4/msgs/mtype.pyi
wxautox4/msgs/self.cp311-win_amd64.pyd
wxautox4/param.py
wxautox4/ui/__init__.py
wxautox4/ui/base.py
wxautox4/ui/chatbox.cp311-win_amd64.pyd
wxautox4/ui/component.cp311-win_amd64.pyd
wxautox4/ui/component.pyi
wxautox4/ui/main.cp311-win_amd64.pyd
wxautox4/ui/moment.cp311-win_amd64.pyd
wxautox4/ui/navigationbox.cp311-win_amd64.pyd
wxautox4/ui/sessionbox.cp311-win_amd64.pyd
wxautox4/uia/__init__.py
wxautox4/uia/uiautomation.py
wxautox4/uia/uiplug.cp311-win_amd64.pyd
wxautox4/utils/__init__.py
wxautox4/utils/lock.py
wxautox4/utils/tools.cp311-win_amd64.pyd
wxautox4/utils/useful.cp311-win_amd64.pyd
wxautox4/utils/win32.cp311-win_amd64.pyd
wxautox4/wx.cp311-win_amd64.pyd
wxautox4/wx.pyi
wxautox4-40.1.4.dist-info/entry_points.txt
wxautox4-40.1.4.dist-info/METADATA
wxautox4-40.1.4.dist-info/WHEEL
wxautox4-40.1.4.dist-info/RECORD
